ppmil/__init__.py
ppmil/_version.py
ppmil/cgf.py
ppmil/gamma.py
ppmil/gto.py
ppmil/molecule.py
ppmil/ppmil.py
ppmil-0.4.0.dist-info/licenses/LICENSE
ppmil-0.4.0.dist-info/METADATA
ppmil-0.4.0.dist-info/WHEEL
ppmil-0.4.0.dist-info/top_level.txt
ppmil-0.4.0.dist-info/RECORD
