Metadata-Version: 2.4
Name: ppmil
Version: 0.4.0
Summary: ppmil
Author-email: Ivo Filot <ivo@ivofilot.nl>
Maintainer-email: Ivo Filot <ivo@ivofilot.nl>
License: GPL-3.0-or-later
Project-URL: Homepage, https://github.com/ifilot/ppmil
Project-URL: Bug Tracker, https://github.com/ifilot/ppmil/issues
Classifier: Programming Language :: Python :: 3
Classifier: Operating System :: OS Independent
Requires-Python: >=3.9
License-File: LICENSE
Requires-Dist: scipy>=1.15
Requires-Dist: numpy
Requires-Dist: pylebedev
Dynamic: license-file
